Metadata-Version: 2.1
Name: CourseSnipe
Version: 1.0.5
Summary: CLI utility for automated enrollment with REM
Home-page: https://github.com/ludanik/CourseSnipe
Author: Ian Ludanik
License: MIT
License-File: LICENSE
Requires-Dist: selenium
Requires-Dist: Click
Requires-Dist: python-dotenv
Requires-Dist: webdriver_manager
